flake8_mock.py
flake8_mock_x2-0.4.1.dist-info/LICENSE
flake8_mock_x2-0.4.1.dist-info/METADATA
flake8_mock_x2-0.4.1.dist-info/WHEEL
flake8_mock_x2-0.4.1.dist-info/entry_points.txt
flake8_mock_x2-0.4.1.dist-info/top_level.txt
flake8_mock_x2-0.4.1.dist-info/RECORD
