Metadata-Version: 2.1
Name: flake8-mock-x2
Version: 0.4.1
Summary: Provides checking for non-existent mock methods and properties
Home-page: https://github.com/aniav/flake8-mock
Author: Anna Warzecha
Author-email: anna.warzecha@gmail.com
License: GNU
Keywords: flake8,mock,testing
Classifier: Development Status :: 3 - Alpha
Classifier: Environment :: Console
Classifier: Intended Audience :: Developers
Classifier: License :: OSI Approved :: GNU General Public License v2 (GPLv2)
Classifier: Operating System :: OS Independent
Classifier: Programming Language :: Python
Classifier: Programming Language :: Python :: 3
Classifier: Topic :: Software Development :: Libraries :: Python Modules
Classifier: Topic :: Software Development :: Quality Assurance
Requires-Python: >=3.0
License-File: LICENSE
Requires-Dist: flake8 (>3.0.0)
